dnsdist_console/__init__.py
dnsdist_console/console.py
dnsdist_console/dashboard.py
dnsdist_console/hashpwd.py
dnsdist_console/key.py
dnsdist_console/statistics.py
dnsdist_console/util.py
dnsdist_console-1.6.0.dist-info/licenses/LICENSE
tests/__init__.py
tests/test_console.py
tests/test_hashpwd.py
tests/test_key.py
tests/test_statistics.py
dnsdist_console-1.6.0.dist-info/METADATA
dnsdist_console-1.6.0.dist-info/WHEEL
dnsdist_console-1.6.0.dist-info/top_level.txt
dnsdist_console-1.6.0.dist-info/RECORD
