Metadata-Version: 2.4
Name: dnsdist_console
Version: 1.6.0
Summary: Python client for dnsdist console
Home-page: https://github.com/dmachard/dnsdist_console
Author: Denis MACHARD
Author-email: d.machard@gmail.com
Keywords: dnsdist console client
Platform: any
Classifier: License :: OSI Approved :: MIT License
Classifier: Programming Language :: Python :: 3
Classifier: Operating System :: OS Independent
Classifier: Topic :: Software Development :: Libraries
License-File: LICENSE
Requires-Dist: libnacl
Requires-Dist: scrypt
Dynamic: author
Dynamic: author-email
Dynamic: classifier
Dynamic: description
Dynamic: description-content-type
Dynamic: home-page
Dynamic: keywords
Dynamic: license-file
Dynamic: platform
Dynamic: requires-dist
Dynamic: summary
